AUTHORS.rst
LICENSE.txt
MANIFEST.in
README.md
requirements.txt
setup.cfg
setup.py
brome/__init__.py
brome.egg-info/PKG-INFO
brome.egg-info/SOURCES.txt
brome.egg-info/dependency_links.txt
brome.egg-info/not-zip-safe
brome.egg-info/requires.txt
brome.egg-info/top_level.txt
brome/admin/__init__.py
brome/admin/app.py
brome/core/__init__.py
brome/core/basetest.py
brome/core/bot_diary.py
brome/core/configurator.py
brome/core/exceptions.py
brome/core/grep.py
brome/core/proxy_driver.py
brome/core/proxy_element.py
brome/core/proxy_element_list.py
brome/core/selector.py
brome/core/settings.py
brome/core/stateful.py
brome/core/utils.py
brome/model/__init__.py
brome/model/basemodel.py
brome/model/test.py
brome/model/testbatch.py
brome/model/testcrash.py
brome/model/testinstance.py
brome/model/testqualityscreenshot.py
brome/model/testresult.py
brome/model/testscreenshot.py
brome/model/user.py
brome/runner/__init__.py
brome/runner/base_instance.py
brome/runner/base_runner.py
brome/runner/browser_config.py
brome/runner/browserstack_instance.py
brome/runner/ec2_instance.py
brome/runner/grid_runner.py
brome/runner/local_runner.py
brome/runner/localhost_instance.py
brome/runner/saucelabs_instance.py
brome/runner/virtualbox_instance.py
brome/webserver/releases/latest.txt
brome/webserver/releases/f152b89c396953b0788db22f30c6c50b7343170a/index.html
brome/webserver/releases/f152b89c396953b0788db22f30c6c50b7343170a/static/1.75e062a38e814b112732.chunk.js
brome/webserver/releases/f152b89c396953b0788db22f30c6c50b7343170a/static/1.75e062a38e814b112732.chunk.js.map
brome/webserver/releases/f152b89c396953b0788db22f30c6c50b7343170a/static/10.75e062a38e814b112732.chunk.js
brome/webserver/releases/f152b89c396953b0788db22f30c6c50b7343170a/static/10.75e062a38e814b112732.chunk.js.map
brome/webserver/releases/f152b89c396953b0788db22f30c6c50b7343170a/static/11.75e062a38e814b112732.chunk.js
brome/webserver/releases/f152b89c396953b0788db22f30c6c50b7343170a/static/11.75e062a38e814b112732.chunk.js.map
brome/webserver/releases/f152b89c396953b0788db22f30c6c50b7343170a/static/12.75e062a38e814b112732.chunk.js
