Metadata-Version: 1.1
Name: brome
Version: 1.2.0
Summary: Selenium Framework
Home-page: https://github.com/jf-parent/brome
Author: Jean-Francois Parent
Author-email: parent.j.f@gmail.com
License: MIT
Keywords: brome,selenium
Platform: UNKNOWN
Classifier: Development Status :: 3 - Alpha
Classifier: Intended Audience :: Developers
Classifier: License :: OSI Approved :: MIT License
Classifier: Natural Language :: English
Classifier: Programming Language :: Python :: 3.5
